<annotation>
	<folder>images</folder>
	<filename>522.jpg</filename>
	<path>C:\Users\derek\Desktop\Image_Processing-main\train\augmented\images\522.jpg</path>
	<source>
		<database>Unknown</database>
	</source>
	<size>
		<width>237</width>
		<height>253</height>
		<depth>3</depth>
	</size>
	<segmented>0</segmented>
	<object>
		<name>rust</name>
		<pose>Unspecified</pose>
		<truncated>0</truncated>
		<difficult>0</difficult>
		<bndbox>
			<xmin>43</xmin>
			<ymin>120</ymin>
			<xmax>167</xmax>
			<ymax>252</ymax>
		</bndbox>
	</object>
</annotation>
